mwdstdcore/__init__.py
mwdstdcore/api/apierror.py
mwdstdcore/api/logs.py
mwdstdcore/api/utils.py
mwdstdcore/api/v1/__init__.py
mwdstdcore/api/v1/core.py
mwdstdcore/api/v1/geomag.py
mwdstdcore/api/v1/hdtraj.py
mwdstdcore/api/v1/lv1b.py
mwdstdcore/api/v1/lv2b.py
mwdstdcore/api/v1/lv3b.py
mwdstdcore/api/v1/mcorrect.py
mwdstdcore/api/v1/meta.py
mwdstdcore/api/v1/models.py
mwdstdcore/api/v1/msa.py
mwdstdcore/api/v1/qc_plan.py
mwdstdcore/api/v1/ref.py
mwdstdcore/api/v1/sag.py
mwdstdcore/auto/act_vs_plan.py
mwdstdcore/auto/autocor.py
mwdstdcore/auto/manualcor.py
mwdstdcore/auto/valid.py
mwdstdcore/cli/mwdhdtraj.py
mwdstdcore/cli/mwdmsa.py
mwdstdcore/cli/mwdsag.py
mwdstdcore/core/analysis/covmat.py
mwdstdcore/core/analysis/emanalysis.py
mwdstdcore/core/analysis/jacobian.py
mwdstdcore/core/common/mincurv.py
mwdstdcore/core/common/src4nrm.py
mwdstdcore/core/common/srvmath.py
mwdstdcore/core/common/vcorrect.py
mwdstdcore/core/common/vdelta.py
mwdstdcore/core/diffev/de_correct.py
mwdstdcore/core/diffev/difev.py
mwdstdcore/core/diffev/search_space.py
mwdstdcore/core/reginc.py
mwdstdcore/core/wfunc.py
mwdstdcore/datamodel/__init__.py
mwdstdcore/datamodel/accu.py
mwdstdcore/datamodel/bha.py
mwdstdcore/datamodel/calc/mincurv.py
mwdstdcore/datamodel/calc/station.py
mwdstdcore/datamodel/calc/survey.py
mwdstdcore/datamodel/cor_survey.py
mwdstdcore/datamodel/correction.py
mwdstdcore/datamodel/dni_params.py
mwdstdcore/datamodel/interval.py
mwdstdcore/datamodel/link.py
mwdstdcore/datamodel/qa.py
mwdstdcore/datamodel/qc_bond.py
mwdstdcore/datamodel/ref.py
mwdstdcore/datamodel/run.py
mwdstdcore/datamodel/station.py
mwdstdcore/datamodel/survey.py
mwdstdcore/datamodel/toolcode.py
mwdstdcore/datamodel/validators.py
mwdstdcore/datamodel/well.py
mwdstdcore/errormods/codes.py
mwdstdcore/errormods/dnimsa.py
mwdstdcore/errormods/dnistd.py
mwdstdcore/errormods/gmagmod.py
mwdstdcore/errormods/posunc/mwdstd.py
mwdstdcore/errormods/posunc/srvmod.py
mwdstdcore/errormods/unknown.py
mwdstdcore-0.7.4.dist-info/entry_points.txt
mwdstdcore-0.7.4.dist-info/LICENSE
mwdstdcore-0.7.4.dist-info/WHEEL
mwdstdcore-0.7.4.dist-info/METADATA
mwdstdcore-0.7.4.dist-info/RECORD
