Metadata-Version: 2.1
Name: mwdstdcore
Version: 0.7.4
Summary: Core project for basic measurement-while-drilling corrections
License: AGPL-3.0-or-later
Author: MWD STD Inc.
Author-email: info@mwdstd.com
Requires-Python: >=3.8,<3.12
Classifier: License :: OSI Approved :: GNU Affero General Public License v3 or later (AGPLv3+)
Classifier: Programming Language :: Python :: 3
Classifier: Programming Language :: Python :: 3.8
Classifier: Programming Language :: Python :: 3.9
Classifier: Programming Language :: Python :: 3.10
Classifier: Programming Language :: Python :: 3.11
Provides-Extra: gunicorn
Requires-Dist: attrs (==21.4.0)
Requires-Dist: click (==8.1.3)
Requires-Dist: colorama (==0.4.5)
Requires-Dist: flask (==2.2.2)
Requires-Dist: gunicorn (==19.10.0); extra == "gunicorn"
Requires-Dist: itsdangerous (==2.1.2)
Requires-Dist: jinja2 (==3.1.2)
Requires-Dist: jsons (==1.6.3)
Requires-Dist: markupsafe (==2.1.1)
Requires-Dist: numpy (==1.23.2)
Requires-Dist: typish (==1.9.3)
Requires-Dist: werkzeug (==2.2.2)
